coininfo_vitaliy/__init__.py
coininfo_vitaliy/info.py
coininfo_vitaliy-0.1.1.dist-info/METADATA
coininfo_vitaliy-0.1.1.dist-info/WHEEL
coininfo_vitaliy-0.1.1.dist-info/top_level.txt
coininfo_vitaliy-0.1.1.dist-info/RECORD
